MyDataSource/__init__.py
MyDataSource/__version__.py
MyDataSource/core.py
MyDataSource-0.1.1.dist-info/LICENSE
MyDataSource-0.1.1.dist-info/METADATA
MyDataSource-0.1.1.dist-info/WHEEL
MyDataSource-0.1.1.dist-info/top_level.txt
MyDataSource-0.1.1.dist-info/RECORD
